isbn_transformer/__init__.py
isbn_transformer/main.py
isbn_transformer/prompts.py
isbn_transformer-2025.12.21113324.dist-info/METADATA
isbn_transformer-2025.12.21113324.dist-info/WHEEL
isbn_transformer-2025.12.21113324.dist-info/top_level.txt
isbn_transformer-2025.12.21113324.dist-info/RECORD
