Metadata-Version: 2.4
Name: isbn-transformer
Version: 2025.12.21113324
Summary: A new package that transforms raw ISBN data into structured, visualizable formats. Users input a list of ISBNs, and the package returns a well-organized, machine-readable output that can be easily vis
Author-email: isbn-transformer <hi@eugene.plus>
License: MIT
Project-URL: Homepage, https://github.com/chigwell/isbn-transformer
Requires-Python: >=3.9
Requires-Dist: langchain-llm7>=0.0.0
Requires-Dist: llmatch-messages>=0.0.0
Requires-Dist: langchain-core>=0.3.0
